{
  "id": "bitd-alternate-sheets-test",
  "title": "Blades in the Dark Alternate Sheets Test Harness",
  "description": "Local-only test helpers for bitd-alternate-sheets.",
  "version": "0.1.0",
  "library": false,
  "compatibility": {
    "minimum": 11,
    "verified": 13
  },
  "authors": [
    {
      "name": "Justin Ross"
    }
  ],
  "relationships": {
    "systems": [
      {
        "id": "blades-in-the-dark",
        "type": "system",
        "manifest": "https://raw.githubusercontent.com/Dez384/foundryvtt-blades-in-the-dark/master/system.json",
        "compatibility": {
          "minimum": "6.0.0"
        }
      }
    ],
    "requires": [
      {
        "id": "bitd-alternate-sheets",
        "type": "module"
      },
      {
        "id": "quench",
        "type": "module"
      }
    ],
    "conflicts": []
  },
  "esmodules": [
    "scripts/module.js",
    "scripts/tests/teeth.test.js",
    "scripts/tests/crew-radio-toggle.test.js",
    "scripts/tests/edit-mode.test.js",
    "scripts/tests/healing-clock.test.js",
    "scripts/tests/crew-sheet.test.js",
    "scripts/tests/crew-member-rerender.test.js",
    "scripts/tests/smart-fields.test.js",
    "scripts/tests/global-clocks.test.js",
    "scripts/tests/update-queue.test.js",
    "scripts/tests/acquaintances.test.js",
    "scripts/tests/compendium-cache.test.js",
    "scripts/tests/npc-integration.test.js",
    "scripts/tests/error-handling.test.js",
    "scripts/tests/binary-checkboxes.test.js",
    "scripts/tests/migration.test.js",
    "scripts/tests/settings.test.js",
    "scripts/tests/crew-link.test.js",
    "scripts/tests/playbook-switching.test.js",
    "scripts/tests/utils-core.test.js",
    "scripts/tests/sheet-popups.test.js",
    "scripts/tests/hooks-integration.test.js",
    "scripts/tests/handlebars-helpers.test.js",
    "scripts/tests/smart-field-custom-text.test.js",
    "scripts/tests/clear-load-button.test.js"
  ]
}
